odoo10_addon_l10n_br_hr_contract-10.0.0.0.0.99.dev11-nspkg.pth
odoo/addons/l10n_br_hr_contract/README.rst
odoo/addons/l10n_br_hr_contract/__init__.py
odoo/addons/l10n_br_hr_contract/__manifest__.py
odoo/addons/l10n_br_hr_contract/data/l10n_br_hr_contract_data.xml
odoo/addons/l10n_br_hr_contract/data/l10n_br_hr_contract_resignation_data.xml
odoo/addons/l10n_br_hr_contract/i18n/l10n_br_hr_contract.pot
odoo/addons/l10n_br_hr_contract/i18n/pt_BR.po
odoo/addons/l10n_br_hr_contract/models/__init__.py
odoo/addons/l10n_br_hr_contract/models/hr_contract.py
odoo/addons/l10n_br_hr_contract/models/hr_contract_admission_type.py
odoo/addons/l10n_br_hr_contract/models/hr_contract_labor_bond_type.py
odoo/addons/l10n_br_hr_contract/models/hr_contract_labor_regime.py
odoo/addons/l10n_br_hr_contract/models/hr_contract_labor_resignation_cause.py
odoo/addons/l10n_br_hr_contract/models/hr_contract_labor_salary_unit.py
odoo/addons/l10n_br_hr_contract/models/hr_contract_notice_termination.py
odoo/addons/l10n_br_hr_contract/security/ir.model.access.csv
odoo/addons/l10n_br_hr_contract/static/description/icon.png
odoo/addons/l10n_br_hr_contract/test/l10n_br_hr_contract_demo.yml
odoo/addons/l10n_br_hr_contract/views/hr_contract_view.xml
odoo10_addon_l10n_br_hr_contract-10.0.0.0.0.99.dev11.dist-info/METADATA
odoo10_addon_l10n_br_hr_contract-10.0.0.0.0.99.dev11.dist-info/WHEEL
odoo10_addon_l10n_br_hr_contract-10.0.0.0.0.99.dev11.dist-info/namespace_packages.txt
odoo10_addon_l10n_br_hr_contract-10.0.0.0.0.99.dev11.dist-info/top_level.txt
odoo10_addon_l10n_br_hr_contract-10.0.0.0.0.99.dev11.dist-info/RECORD
